airflow_ansible_provider/__init__.py
airflow_ansible_provider/plugins.py
airflow_ansible_provider/decorators/__init__.py
airflow_ansible_provider/decorators/ansible_decorators.py
airflow_ansible_provider/hooks/__init__.py
airflow_ansible_provider/hooks/ansible.py
airflow_ansible_provider/operators/__init__.py
airflow_ansible_provider/operators/ansible_operator.py
airflow_ansible_provider/utils/__init__.py
airflow_ansible_provider/utils/sync_git_repo.py
airflow_ansible_provider-0.6.0.dist-info/licenses/LICENSE
airflow_ansible_provider-0.6.0.dist-info/METADATA
airflow_ansible_provider-0.6.0.dist-info/WHEEL
airflow_ansible_provider-0.6.0.dist-info/entry_points.txt
airflow_ansible_provider-0.6.0.dist-info/top_level.txt
airflow_ansible_provider-0.6.0.dist-info/RECORD
