Metadata-Version: 2.4
Name: airflow-ansible-provider
Version: 0.6.0
Summary: Enables execution of Ansible Task from Airflow
Home-page: https://github.com/liuzheng/airflow-ansible-provider
Author: liuzheng
Author-email: liuzheng <liuzheng712@gmail.com>
License: Apache Software License
Project-URL: Homepage, https://github.com/liuzheng/airflow-ansible-provider
Project-URL: Bug Tracker, https://github.com/liuzheng/airflow-ansible-provider/issues
Classifier: Programming Language :: Python :: 3
Classifier: License :: OSI Approved :: Apache Software License
Classifier: Operating System :: OS Independent
Requires-Python: >=3.8.0
License-File: LICENSE
Requires-Dist: apache-airflow>=2.0.0
Requires-Dist: ansible-runner>=2.0.0
Requires-Dist: ansible>=6.0.0
Requires-Dist: packaging
Requires-Dist: boto3
Dynamic: license-file
